odoo10_addon_web_openeducat-10.0.3.0.0-py2.7-nspkg.pth
odoo/addons/web_openeducat/README.rst
odoo/addons/web_openeducat/__init__.py
odoo/addons/web_openeducat/__manifest__.py
odoo/addons/web_openeducat/static/description/icon.png
odoo/addons/web_openeducat/static/description/index.html
odoo/addons/web_openeducat/static/description/openeducat_logo.png
odoo/addons/web_openeducat/static/description/web_home_page.png
odoo/addons/web_openeducat/static/description/web_openeducat_banner.jpg
odoo/addons/web_openeducat/static/js/countUp.js
odoo/addons/web_openeducat/static/js/custom.js
odoo/addons/web_openeducat/static/src/img/about-sec-img.png
odoo/addons/web_openeducat/static/src/img/arrow.png
odoo/addons/web_openeducat/static/src/img/banner_image.jpg
odoo/addons/web_openeducat/static/src/img/banner_image1.jpg
odoo/addons/web_openeducat/static/src/img/blog1.jpg
odoo/addons/web_openeducat/static/src/img/blog2.jpg
odoo/addons/web_openeducat/static/src/img/blog3.jpg
odoo/addons/web_openeducat/static/src/img/carousel.png
odoo/addons/web_openeducat/static/src/img/center-achieve-1.jpg
odoo/addons/web_openeducat/static/src/img/center-achieve.jpg
odoo/addons/web_openeducat/static/src/img/img-04.jpg
odoo/addons/web_openeducat/static/src/img/logo.png
odoo/addons/web_openeducat/static/src/img/popular_courses1.jpg
odoo/addons/web_openeducat/static/src/img/popular_courses2.jpg
odoo/addons/web_openeducat/static/src/img/popular_courses3.jpg
odoo/addons/web_openeducat/static/src/img/popular_courses4.jpg
odoo/addons/web_openeducat/static/src/img/popular_courses5.jpg
odoo/addons/web_openeducat/static/src/img/popular_courses6.jpg
odoo/addons/web_openeducat/static/src/img/popular_courses7.jpg
odoo/addons/web_openeducat/static/src/img/popular_courses8.jpg
odoo/addons/web_openeducat/static/src/img/scale.png
odoo/addons/web_openeducat/static/src/img/scale1.png
odoo/addons/web_openeducat/static/src/img/scale2.png
odoo10_addon_web_openeducat-10.0.3.0.0.dist-info/DESCRIPTION.rst
odoo10_addon_web_openeducat-10.0.3.0.0.dist-info/METADATA
odoo10_addon_web_openeducat-10.0.3.0.0.dist-info/RECORD
odoo10_addon_web_openeducat-10.0.3.0.0.dist-info/WHEEL
odoo10_addon_web_openeducat-10.0.3.0.0.dist-info/metadata.json
odoo10_addon_web_openeducat-10.0.3.0.0.dist-info/namespace_packages.txt
odoo10_addon_web_openeducat-10.0.3.0.0.dist-info/top_level.txt
