Metadata-Version: 2.0
Name: odoo10-addon-web-openeducat
Version: 10.0.3.0.0
Summary: Web OpenEduCat
Home-page: http://www.openeducat.org
Author: Tech Receptives
Author-email: UNKNOWN
License: LGPL-3
Platform: UNKNOWN
Classifier: Programming Language :: Python :: 2.7
Classifier: Framework :: Odoo
Classifier: License :: OSI Approved :: GNU Lesser General Public License v3 (LGPLv3)
Requires-Dist: odoo (<10.1dev,>=10.0)
